LICENSE
README.md
setup.cfg
setup.py
harvest/__init__.py
harvest/harvest.py
harvest_for_mightyhive.egg-info/PKG-INFO
harvest_for_mightyhive.egg-info/SOURCES.txt
harvest_for_mightyhive.egg-info/dependency_links.txt
harvest_for_mightyhive.egg-info/requires.txt
harvest_for_mightyhive.egg-info/top_level.txt