Metadata-Version: 2.1
Name: harvest-for-mightyhive
Version: 0.0.2
Summary: An automation tool to speed up the process of updating entries in harvest
Home-page: https://github.com/superyang713/harvest_automation/blob/main/README.md
Author: Yang Dai
Author-email: yang.dai2020@gmail.com
License: UNKNOWN
Download-URL: https://github.com/superyang713/harvest_automation/archive/refs/tags/v0.0.2.tar.gz
Platform: UNKNOWN
Classifier: Programming Language :: Python :: 3
Classifier: License :: OSI Approved :: MIT License
Classifier: Operating System :: OS Independent
Classifier: Topic :: Software Development :: Build Tools
Classifier: Intended Audience :: Developers
Classifier: Development Status :: 3 - Alpha
License-File: LICENSE
